django_restify
