Metadata-Version: 1.1
Name: django-restify
Version: 0.1.6
Summary: Turn your Django project into RESTFul APIs in a minute.
Home-page: https://github.com/s2krish/django-restify
Author: Krish
Author-email: krish@jaljale.com
License: UNKNOWN
Keywords: django,restfulapi,rest apis
Platform: UNKNOWN
Classifier: Development Status :: 5 - Production/Stable
Classifier: Environment :: Web Environment
Classifier: Framework :: Django
Classifier: Framework :: Django :: 1.8
Classifier: Intended Audience :: Developers
Classifier: License :: OSI Approved :: BSD License
Classifier: Natural Language :: English
Classifier: Operating System :: OS Independent
Classifier: Programming Language :: Python
Classifier: Programming Language :: Python :: 3
Classifier: Topic :: Internet :: WWW/HTTP
